{
  "filename": "KakaoTalk_Photo_2025-11-15-00-02-23 003.jpeg",
  "date": "2025-01-19",
  "service": "2부예배",
  "anthem": "오 놀라운 구세주",
  "offering_hymn_leader": "두나미스",
  "total": 82,
  "breakdown": {
    "soprano": 32,
    "alto": 23,
    "tenor": 13,
    "bass": 14
  },
  "rows": [
    {
      "row": 1,
      "members": [
        "김소라",
        "이은혜",
        "추민아",
        "이선미",
        "김문희",
        "서헌숙",
        "김경희",
        "김혜선",
        "강혜선",
        "심희숙",
        "민은홍",
        "김소옥",
        "안은희",
        "최명희",
        "이건자"
      ]
    },
    {
      "row": 2,
      "members": [
        "양승진",
        "이광숙",
        "손기순",
        "문희",
        "오연분",
        "신수정",
        "방진경",
        "이영란",
        "이혜연",
        "이윤옥",
        "최연희",
        "김영정",
        "김수영",
        "최유진",
        "이은주"
      ]
    },
    {
      "row": 3,
      "members": [
        "현성희",
        "노은숙",
        "김지영",
        "이선아",
        "이수지",
        "김지혜",
        "김은혜",
        "최해경",
        "백성원",
        "이상미",
        "김이정",
        "김은영",
        "김윤희",
        "최승운"
      ]
    },
    {
      "row": 4,
      "members": [
        "안강현",
        "김상목",
        "오홍철",
        "권인영",
        "백한나",
        "신나래",
        "이승숙",
        "임신애",
        "염용주",
        "김희진",
        "양아름",
        "김대영",
        "남승호",
        "이기형"
      ]
    },
    {
      "row": 5,
      "members": [
        "김재관",
        "정진문",
        "이강봉",
        "최광열",
        "임서연",
        "김진희",
        "김정숙",
        "강재은",
        "한만영",
        "김창동",
        "최신규",
        "최종현",
        "이원섭"
      ]
    },
    {
      "row": 6,
      "members": [
        "김학영",
        "정현석",
        "최창운",
        "이상조",
        "이승균",
        "임삼진",
        "김철우",
        "박재용",
        "하범",
        "문승현",
        "김택훈"
      ]
    }
  ]
}